csi/__init__.py
csi/api_errors.py
csi/csi_connector.py
csi/csv_writer.py
test/__init__.py
test/test_operations.py
csi_tai-0.0.23.dist-info/LICENSE
csi_tai-0.0.23.dist-info/METADATA
csi_tai-0.0.23.dist-info/WHEEL
csi_tai-0.0.23.dist-info/top_level.txt
csi_tai-0.0.23.dist-info/RECORD
