Metadata-Version: 2.1
Name: csi-tai
Version: 0.0.23
Summary: A connector to simplify interactions with CSI / Virtial Observer web api
Home-page: https://github.com/dtaivpp/CSI_API
Author: David Tippett
Author-email: dtaivpp@gmail.com
License: UNKNOWN
Keywords: virtual observer csi api integration
Platform: UNKNOWN
Classifier: Programming Language :: Python :: 3
Classifier: License :: OSI Approved :: MIT License
Classifier: Intended Audience :: Developers
Classifier: Operating System :: OS Independent
Classifier: Development Status :: 3 - Alpha
